{"definitions": {"Is.Building.Layer": ["==", ["get", "$layer"], "buildings"], "Is.Building.Label.Layer": ["==", ["get", "$layer"], "buildings"], "Is.Building": ["==", ["get", "kind"], "building"], "Is.Building.Address.Layer": ["==", ["get", "kind"], "address"], "Is.Special.Building": ["ref", "Is.Special.Building.RoW"], "Is.Special.Building.RoW": ["any", ["in", ["get", "kind_detail"], ["literal", ["civic", "courthouse", "embassy", "fire_station", "government", "historical", "hospital", "landmark", "police", "townhall"]]], ["all", ["in", ["get", "kind_detail"], ["literal", ["airport", "art", "arts_centre", "bus_station", "church", "cinema", "educational_institution", "hotel", "inclined_rail_station", "library", "monorail_station", "mosque", "museum", "religion", "school", "synagogue", "temple", "theatre", "train_station", "transportation", "university"]]], ["any", [">=", ["get", "height"], 6], ["!", ["has", "height"]]]], ["all", ["in", ["get", "kind_detail"], ["literal", ["casino", "department_store", "mall", "marina", "nightclub", "retail", "ski", "sports", "tourism", "trade"]]], [">=", ["get", "height"], 15]], ["all", ["in", ["get", "kind_detail"], ["literal", ["bank", "commercial", "mixed_use", "office", "post_office"]]], [">=", ["get", "height"], 25]], ["all", ["in", ["get", "kind_detail"], ["literal", ["factory", "industrial", "winery"]]], [">=", ["get", "height"], 35]], ["all", ["in", ["get", "kind_detail"], ["literal", ["bridge", "park", "parking", "passageway", "staircase", "toll_booth"]]], [">=", ["get", "height"], 15]], ["all", ["in", ["get", "kind_detail"], ["literal", ["bar", "books", "car", "car_rental", "car_repair", "clothes", "convenience", "electronics", "fuel", "grocery", "pharmacy", "restaurant"]]], [">=", ["get", "height"], 10]], [">=", ["get", "height"], 60]], "Is.Building.Underground.TrainStation": false, "Is.Transit.Layer": false}}